Workbook
Name Aporte: AnálisesInvestimentos!$D$15
Name Patrimonio: AnálisesInvestimentos!$D$18
Name QtdAnos: AnálisesInvestimentos!$D$16
Name RendimentoCarteira: AnálisesInvestimentos!$D$11
Name Salario: AnálisesInvestimentos!$D$10
Name SugestaoInvestimento: AnálisesInvestimentos!$D$12

Sheet Dados
A2: CHAVE | B2: PERFIL | C2: TIPO DE FII | D2: %
A3: =B3&"-"&C3 -> Conservador-PAPEL | B3: Conservador | C3: PAPEL | D3: 0.3 | H3: %
A4: =B4&"-"&C4 -> Conservador-TIJOLO | B4: Conservador | C4: TIJOLO | D4: 0.5 | G4: Moderado-TIJOLO | H4: =VLOOKUP(G4,$A:$D,4,FALSE) -> 0.35
A5: =B5&"-"&C5 -> Conservador-HÍBRIDOS | B5: Conservador | C5: HÍBRIDOS | D5: 0.1
A6: =B6&"-"&C6 -> Conservador-FOFs | B6: Conservador | C6: FOFs | D6: 0.1
A7: =B7&"-"&C7 -> Conservador-DESENVOLVIMENTO | B7: Conservador | C7: DESENVOLVIMENTO | D7: 0
A8: =B8&"-"&C8 -> Conservador-HOTELARIAS | B8: Conservador | C8: HOTELARIAS | D8: 0
A9: =B9&"-"&C9 -> Moderado-PAPEL | B9: Moderado | C9: PAPEL | D9: 0.32
A10: =B10&"-"&C10 -> Moderado-TIJOLO | B10: Moderado | C10: TIJOLO | D10: 0.35
A11: =B11&"-"&C11 -> Moderado-HÍBRIDOS | B11: Moderado | C11: HÍBRIDOS | D11: 0.08
A12: =B12&"-"&C12 -> Moderado-FOFs | B12: Moderado | C12: FOFs | D12: 0.05
A13: =B13&"-"&C13 -> Moderado-DESENVOLVIMENTO | B13: Moderado | C13: DESENVOLVIMENTO | D13: 0.1
A14: =B14&"-"&C14 -> Moderado-HOTELARIAS | B14: Moderado | C14: HOTELARIAS | D14: 0.1
A15: =B15&"-"&C15 -> Agressivo-PAPEL | B15: Agressivo | C15: PAPEL | D15: 0.5
A16: =B16&"-"&C16 -> Agressivo-TIJOLO | B16: Agressivo | C16: TIJOLO | D16: 0.1
... A20: =B20&"-"&C20 -> Agressivo-HOTELARIAS | B20: Agressivo | C20: HOTELARIAS | D20: 0.1

Sheet AnálisesInvestimentos
B9: CONFIGURAÇÕES
B10: Salário | D10: 7500
B11: Rendimento da Carteira | D11: 0.01079
B12: Sugestão de Investimento | D12: =Salario*0.3 -> 2250
B14: INVESTIMENTO MENSAL
B15: Quanto investir por mês ? | D15: 1500
B16: Por Quantos Anos ? | D16: 10
B17: Taxa de Rendimento mensal ? | D17: =RendimentoCarteira -> 0.01079
B18: Patrimônio acumulado ? | D18: =FV(RendimentoCarteira,QtdAnos*12,Aporte)*-1 -> 364926.32
B19: Dividendos Mensais ? | D19: =Patrimonio*RendimentoCarteira -> 3937.555
B21: CENÁRIOS | C21: Valor R$ | D21: Dividendos R$
A22: 2 | B22: Acumulado em 2 Anos | C22: =FV($D$17,$A22*12,$D$15)*-1 -> 40841.441 | D22: =C22*RendimentoCarteira -> 440.67915
A23: 5 | B23: Acumulado em 5 Anos | C23: =FV($D$17,$A23*12,$D$15)*-1 -> 125665.37 | D23: =C23*RendimentoCarteira -> 1355.9294
A24: 10 | B24: Acumulado em 10 Anos | C24: =FV($D$17,$A24*12,$D$15)*-1 -> 364926.32 | D24: =C24*RendimentoCarteira -> 3937.555
A25: 20 | B25: Acumulado em 20 Anos | C25: =FV($D$17,$A25*12,$D$15)*-1 -> 1687797.6 | D25: =C25*RendimentoCarteira -> 18211.336
A26: 30 | B26: Acumulado em 30 Anos | C26: =FV($D$17,$A26*12,$D$15)*-1 -> 6483254.5 | D26: =C26*RendimentoCarteira -> 69954.316
B30: PERFIL DO INVESTIDOR | D30: AGRESSIVO
B31: Valor do Investimento Mensal | D31: =Aporte -> 1500
B33: TIPOS DE FII | C33: PERCENTUAL SUGERIDO | D33: VALORES R$
B34: PAPEL | C34: =VLOOKUP($D$30&"-"&B34,'Tabela de Apoio'!A2:D20,4,0) -> 0.5 | D34: =Aporte*C34 -> 750
B35: TIJOLO | C35: =VLOOKUP($D$30&"-"&B35,'Tabela de Apoio'!A3:D21,4,0) -> 0.1 | D35: =Aporte*C35 -> 150
B36: HÍBRIDOS | C36: =VLOOKUP($D$30&"-"&B36,'Tabela de Apoio'!A4:D22,4,0) -> 0.05 | D36: =Aporte*C36 -> 75
B37: FOFs | C37: =VLOOKUP($D$30&"-"&B37,'Tabela de Apoio'!A5:D23,4,0) -> 0.05 | D37: =Aporte*C37 -> 75
B38: DESENVOLVIMENTO | C38: =VLOOKUP($D$30&"-"&B38,'Tabela de Apoio'!A6:D24,4,0) -> 0.2 | D38: =Aporte*C38 -> 300
B39: HOTELARIA | C39: =VLOOKUP($D$30&"-"&B39,'Tabela de Apoio'!A7:D25,4,0) -> 0.1 | D39: =Aporte*C39 -> 150
D40: =SUM(D34:D39) -> 1500

Sheet Tabela de Apoio
A2: CHAVE COMPOSTA | B2: PERFIL | C2: TIPOS DE FII | D2: %
A3: =B3&"-"&C3 -> CONSERVADOR-PAPEL | B3: CONSERVADOR | C3: PAPEL | D3: 0.3
A4: =B4&"-"&C4 -> CONSERVADOR-TIJOLO | B4: CONSERVADOR | C4: TIJOLO | D4: 0.5
A5: =B5&"-"&C5 -> CONSERVADOR-HÍBRIDOS | B5: CONSERVADOR | C5: HÍBRIDOS | D5: 0.1
A6: =B6&"-"&C6 -> CONSERVADOR-FOFs | B6: CONSERVADOR | C6: FOFs | D6: 0.1
A7: =B7&"-"&C7 -> CONSERVADOR-DESENVOLVIMENTO | B7: CONSERVADOR | C7: DESENVOLVIMENTO | D7: 0
A8: =B8&"-"&C8 -> CONSERVADOR-HOTELARIA | B8: CONSERVADOR | C8: HOTELARIA | D8: 0
A9: =B9&"-"&C9 -> MODERADO-PAPEL | B9: MODERADO | C9: PAPEL | D9: 0.32
A10: =B10&"-"&C10 -> MODERADO-TIJOLO | B10: MODERADO | C10: TIJOLO | D10: 0.3
A11: =B11&"-"&C11 -> MODERADO-HÍBRIDOS | B11: MODERADO | C11: HÍBRIDOS | D11: 0.08
A12: =B12&"-"&C12 -> MODERADO-FOFs | B12: MODERADO | C12: FOFs | D12: 0.1
A13: =B13&"-"&C13 -> MODERADO-DESENVOLVIMENTO | B13: MODERADO | C13: DESENVOLVIMENTO | D13: 0.1
A14: =B14&"-"&C14 -> MODERADO-HOTELARIA | B14: MODERADO | C14: HOTELARIA | D14: 0.1
... A20: =B20&"-"&C20 -> AGRESSIVO-HOTELARIA | B20: AGRESSIVO | C20: HOTELARIA | D20: 0.1
